neurobus/__init__.py
neurobus/__version__.py
neurobus/py.typed
neurobus/config/__init__.py
neurobus/config/defaults.py
neurobus/config/loader.py
neurobus/config/schema.py
neurobus/config/validator.py
neurobus/context/__init__.py
neurobus/context/dsl.py
neurobus/context/engine.py
neurobus/context/filter.py
neurobus/context/store.py
neurobus/core/__init__.py
neurobus/core/bus.py
neurobus/core/dispatcher.py
neurobus/core/event.py
neurobus/core/lifecycle.py
neurobus/core/registry.py
neurobus/core/subscription.py
neurobus/distributed/__init__.py
neurobus/distributed/cluster.py
neurobus/distributed/redis_backend.py
neurobus/exceptions/__init__.py
neurobus/exceptions/core.py
neurobus/exceptions/memory.py
neurobus/exceptions/semantic.py
neurobus/exceptions/temporal.py
neurobus/llm/__init__.py
neurobus/llm/bridge.py
neurobus/llm/connector.py
neurobus/llm/hooks.py
neurobus/llm/reasoning.py
neurobus/llm/providers/__init__.py
neurobus/llm/providers/ollama.py
neurobus/memory/__init__.py
neurobus/memory/adapter.py
neurobus/memory/engine.py
neurobus/memory/lancedb_adapter.py
neurobus/memory/qdrant_adapter.py
neurobus/memory/store.py
neurobus/monitoring/__init__.py
neurobus/monitoring/metrics.py
neurobus/semantic/__init__.py
neurobus/semantic/cache.py
neurobus/semantic/encoder.py
neurobus/semantic/router.py
neurobus/semantic/similarity.py
neurobus/temporal/__init__.py
neurobus/temporal/causality.py
neurobus/temporal/engine.py
neurobus/temporal/store.py
neurobus/types/__init__.py
neurobus/types/context.py
neurobus/types/events.py
neurobus/types/protocols.py
neurobus/types/subscriptions.py
neurobus/utils/__init__.py
neurobus/utils/helpers.py
neurobus/utils/patterns.py
neurobus/utils/serialization.py
neurobus/utils/timing.py
neurobus/utils/validation.py
neurobus-1.0.0.dist-info/licenses/LICENSE
neurobus-1.0.0.dist-info/METADATA
neurobus-1.0.0.dist-info/WHEEL
neurobus-1.0.0.dist-info/top_level.txt
neurobus-1.0.0.dist-info/RECORD
