Metadata-Version: 2.4
Name: neurobus
Version: 1.0.0
Summary: The World's First Neuro-Semantic Event Bus for Cognitive AI Systems
Home-page: https://github.com/eshanized/neurobus
Author: Eshan Roy
Author-email: Eshan Roy <eshanized@proton.me>
License: MIT
Project-URL: Homepage, https://github.com/eshanized/neurobus
Project-URL: Documentation, https://neurobus.readthedocs.io
Project-URL: Repository, https://github.com/eshanized/neurobus
Project-URL: Bug Tracker, https://github.com/eshanized/neurobus/issues
Project-URL: Changelog, https://github.com/eshanized/neurobus/blob/main/CHANGELOG.md
Keywords: event-bus,semantic-routing,cognitive-ai,llm,vector-database,distributed-systems
Classifier: Development Status :: 5 - Production/Stable
Classifier: Intended Audience :: Developers
Classifier: License :: OSI Approved :: MIT License
Classifier: Programming Language :: Python :: 3.11
Classifier: Programming Language :: Python :: 3.12
Classifier: Programming Language :: Python :: 3.13
Classifier: Topic :: Software Development :: Libraries :: Python Modules
Classifier: Topic :: Scientific/Engineering :: Artificial Intelligence
Classifier: Topic :: System :: Distributed Computing
Classifier: Framework :: AsyncIO
Classifier: Typing :: Typed
Classifier: Operating System :: OS Independent
Requires-Python: >=3.11
License-File: LICENSE
Requires-Dist: pydantic>=2.0.0
Requires-Dist: pyyaml>=6.0
Requires-Dist: aiofiles>=23.0.0
Provides-Extra: semantic
Requires-Dist: sentence-transformers>=2.2.0; extra == "semantic"
Requires-Dist: torch>=2.0.0; extra == "semantic"
Requires-Dist: numpy>=1.24.0; extra == "semantic"
Provides-Extra: qdrant
Requires-Dist: qdrant-client>=1.7.0; extra == "qdrant"
Provides-Extra: lancedb
Requires-Dist: lancedb>=0.3.0; extra == "lancedb"
Requires-Dist: pyarrow>=12.0.0; extra == "lancedb"
Provides-Extra: memory
Requires-Dist: qdrant-client>=1.7.0; extra == "memory"
Requires-Dist: lancedb>=0.3.0; extra == "memory"
Requires-Dist: pyarrow>=12.0.0; extra == "memory"
Provides-Extra: openai
Requires-Dist: openai>=1.12.0; extra == "openai"
Provides-Extra: anthropic
Requires-Dist: anthropic>=0.18.0; extra == "anthropic"
Provides-Extra: ollama
Requires-Dist: httpx>=0.25.0; extra == "ollama"
Provides-Extra: llm
Requires-Dist: openai>=1.12.0; extra == "llm"
Requires-Dist: anthropic>=0.18.0; extra == "llm"
Requires-Dist: httpx>=0.25.0; extra == "llm"
Provides-Extra: distributed
Requires-Dist: redis>=5.0.0; extra == "distributed"
Provides-Extra: monitoring
Requires-Dist: prometheus-client>=0.19.0; extra == "monitoring"
Provides-Extra: all
Requires-Dist: sentence-transformers>=2.2.0; extra == "all"
Requires-Dist: torch>=2.0.0; extra == "all"
Requires-Dist: numpy>=1.24.0; extra == "all"
Requires-Dist: qdrant-client>=1.7.0; extra == "all"
Requires-Dist: lancedb>=0.3.0; extra == "all"
Requires-Dist: pyarrow>=12.0.0; extra == "all"
Requires-Dist: openai>=1.12.0; extra == "all"
Requires-Dist: anthropic>=0.18.0; extra == "all"
Requires-Dist: httpx>=0.25.0; extra == "all"
Requires-Dist: redis>=5.0.0; extra == "all"
Requires-Dist: prometheus-client>=0.19.0; extra == "all"
Provides-Extra: dev
Requires-Dist: pytest>=7.4.0; extra == "dev"
Requires-Dist: pytest-asyncio>=0.21.0; extra == "dev"
Requires-Dist: pytest-cov>=4.1.0; extra == "dev"
Requires-Dist: pytest-mock>=3.12.0; extra == "dev"
Requires-Dist: black>=23.12.0; extra == "dev"
Requires-Dist: ruff>=0.1.0; extra == "dev"
Requires-Dist: mypy>=1.8.0; extra == "dev"
Requires-Dist: types-PyYAML; extra == "dev"
Requires-Dist: types-aiofiles; extra == "dev"
Dynamic: author
Dynamic: home-page
Dynamic: license-file
Dynamic: requires-python
